README.md
setup.py
fsmodels/__init__.py
fsmodels/common.py
fsmodels/fields.py
fsmodels/models.py
fsmodels/utils.py
fsmodels.egg-info/PKG-INFO
fsmodels.egg-info/SOURCES.txt
fsmodels.egg-info/dependency_links.txt
fsmodels.egg-info/requires.txt
fsmodels.egg-info/top_level.txt
tests/__init__.py
tests/test_field.py
tests/test_model.py
tests/test_modelField.py