Metadata-Version: 1.2
Name: fsmodels
Version: 0.1.0.dev0
Summary: This library serves as a wrapper around Google's Firestore. It implements validation, type checking facilities, and relational (work in progress) model logic.
Home-page: https://github.com/CorrDyn/python-firestore-models
Author: John-Paul Jorissen
Author-email: jjorissen52@gmail.com
License: Apache
Keywords: Python Firestore Models ORM Wrapper
Platform: UNKNOWN
Classifier: Development Status :: 3 - Alpha
Classifier: Intended Audience :: Developers
Classifier: Programming Language :: Python :: 3.6
Classifier: Operating System :: Microsoft :: Windows :: Windows 10
Classifier: Operating System :: POSIX :: Linux
Classifier: License :: OSI Approved :: Apache Software License
Classifier: Programming Language :: Python :: 3.6
Classifier: Programming Language :: Python :: 3.7
Requires-Python: >=3.6
